lektor_jinja_helpers-0.1.0.dist-info/METADATA
lektor_jinja_helpers-0.1.0.dist-info/WHEEL
lektor_jinja_helpers-0.1.0.dist-info/entry_points.txt
lektor_jinja_helpers-0.1.0.dist-info/licenses/LICENSE
lektor_jinja_helpers/__init__.py
lektor_jinja_helpers/ansible.py
lektor_jinja_helpers/db_helpers.py
lektor_jinja_helpers/html_helpers.py
lektor_jinja_helpers/misc_helpers.py
lektor_jinja_helpers/py.typed
lektor_jinja_helpers-0.1.0.dist-info/RECORD
