Metadata-Version: 2.1
Name: lektor-jinja-helpers
Version: 0.1.0
Summary: An assortment of Jinja filters, tests, and globals for Lektor
Keywords: lektor plugin jinja filters jinja tests jinja globals
Author-Email: Jeff Dairiki <dairiki@dairiki.org>
License: BSD-3-Clause
Classifier: Development Status :: 3 - Alpha
Classifier: Environment :: Plugins
Classifier: Environment :: Web Environment
Classifier: Framework :: Lektor
Classifier: Intended Audience :: Developers
Classifier: License :: OSI Approved :: MIT License
Classifier: Programming Language :: Python :: 3
Classifier: Programming Language :: Python :: 3.8
Classifier: Programming Language :: Python :: 3.9
Classifier: Programming Language :: Python :: 3.10
Classifier: Programming Language :: Python :: 3.11
Classifier: Programming Language :: Python :: 3.12
Classifier: Topic :: Text Processing
Classifier: Typing :: Typed
Project-URL: Homepage, https://github.com/dairiki/lektor-jinja-helpers
Requires-Python: >=3.8
Requires-Dist: excerpt-html>=0.2.0
Requires-Dist: markupsafe>=2.1.3
Requires-Dist: html5lib>=1.1
Requires-Dist: beautifulsoup4>=4.12.2
Requires-Dist: typing-extensions>=4.7.1; python_version < "3.12"
Requires-Dist: ansible-core>=2.13; extra == "ansible"
Requires-Dist: ansible; extra == "ansible-full"
Requires-Dist: ansible-core>=2.13; extra == "ansible-full"
Provides-Extra: ansible
Provides-Extra: ansible-full
